LICENSE
README.md
setup.py
faxdatasdk/__init__.py
faxdatasdk/api.py
faxdatasdk/client.py
faxdatasdk/exceptions.py
faxdatasdk/logger.py
faxdatasdk/request.py
faxdatasdk/thrift_client.py
faxdatasdk/utils.py
faxdatasdk/version.py
faxdatasdk.egg-info/PKG-INFO
faxdatasdk.egg-info/SOURCES.txt
faxdatasdk.egg-info/dependency_links.txt
faxdatasdk.egg-info/not-zip-safe
faxdatasdk.egg-info/requires.txt
faxdatasdk.egg-info/top_level.txt
faxdatasdk/compat/__init__.py
faxdatasdk/compat/pickle_compat.py