Metadata-Version: 2.1
Name: faxdatasdk
Version: 0.0.14
Summary: Data SDK for stock analysis.
Home-page: https://www.faxframework.com
Author: PinkQuant
Author-email: tickertrading@163.com
Maintainer: topbip
Maintainer-email: pinkquant@163.com
License: Apache License v2
Platform: all
Classifier: Programming Language :: Python
Classifier: Operating System :: Microsoft :: Windows
Classifier: Operating System :: Unix
Classifier: Development Status :: 3 - Alpha
Classifier: Intended Audience :: Developers
Classifier: Programming Language :: Python :: 3.8
License-File: LICENSE
